perfcount/__init__.py
perfcount/__main__.py
perfcount/time_this_program.py
perfcount-1.0.1.dist-info/entry_points.txt
perfcount-1.0.1.dist-info/LICENSE
perfcount-1.0.1.dist-info/WHEEL
perfcount-1.0.1.dist-info/METADATA
perfcount-1.0.1.dist-info/RECORD
