Metadata-Version: 2.1
Name: perfcount
Version: 1.0.1
Summary: Useful Python library for performance testing that contains multiple function decorators
Keywords: testing,performance,timing,timeout,debugger,acceptance
Author-email: Carl Furtado <carlzfurtado@gmail.com>
Classifier: License :: OSI Approved :: MIT License
Classifier: Programming Language :: Python
Classifier: Programming Language :: Python :: 3
Classifier: Operating System :: OS Independent
Classifier: Intended Audience :: Developers
Classifier: Topic :: Software Development :: Debuggers
Classifier: Topic :: Software Development :: Testing
Classifier: Topic :: Software Development :: Testing :: Acceptance
Project-URL: Home, https://github.com/User0332/perfcount
